LICENSE.md
alns/ALNS.py
alns/Outcome.py
alns/Result.py
alns/State.py
alns/Statistics.py
alns/__init__.py
alns/accept/AcceptanceCriterion.py
alns/accept/AlwaysAccept.py
alns/accept/GreatDeluge.py
alns/accept/HillClimbing.py
alns/accept/LateAcceptanceHillClimbing.py
alns/accept/MovingAverageThreshold.py
alns/accept/NonLinearGreatDeluge.py
alns/accept/RandomAccept.py
alns/accept/RecordToRecordTravel.py
alns/accept/SimulatedAnnealing.py
alns/accept/__init__.py
alns/accept/tests/__init__.py
alns/accept/tests/test_great_deluge.py
alns/accept/tests/test_hill_climbing.py
alns/accept/tests/test_late_acceptance_hill_climbing.py
alns/accept/tests/test_moving_average_threshold.py
alns/accept/tests/test_non_linear_great_deluge.py
alns/accept/tests/test_random_accept.py
alns/accept/tests/test_random_walk.py
alns/accept/tests/test_record_to_record_travel.py
alns/accept/tests/test_simulated_annealing.py
alns/accept/tests/test_threshold_accept.py
alns/accept/tests/test_update.py
alns/accept/update.py
alns/select/AlphaUCB.py
alns/select/MABSelector.py
alns/select/OperatorSelectionScheme.py
alns/select/RandomSelect.py
alns/select/RouletteWheel.py
alns/select/SegmentedRouletteWheel.py
alns/select/__init__.py
alns/select/tests/__init__.py
alns/select/tests/test_alpha_ucb.py
alns/select/tests/test_mab_selector.py
alns/select/tests/test_random_select.py
alns/select/tests/test_roulette_wheel.py
alns/select/tests/test_segmented_roulette_wheel.py
alns/show_versions.py
alns/stop/MaxIterations.py
alns/stop/MaxRuntime.py
alns/stop/NoImprovement.py
alns/stop/StoppingCriterion.py
alns/stop/__init__.py
alns/stop/tests/__init__.py
alns/stop/tests/test_max_iterations.py
alns/stop/tests/test_max_runtime.py
alns/stop/tests/test_no_improvement.py
alns/tests/__init__.py
alns/tests/conftest.py
alns/tests/states.py
alns/tests/test_alns.py
alns/tests/test_result.py
alns/tests/test_statistics.py
alns-6.0.0.dist-info/LICENSE.md
alns-6.0.0.dist-info/METADATA
alns-6.0.0.dist-info/WHEEL
alns-6.0.0.dist-info/RECORD
