Metadata-Version: 2.1
Name: alns
Version: 6.0.0
Summary: A flexible implementation of the adaptive large neighbourhood search (ALNS) algorithm.
Home-page: https://github.com/N-Wouda/ALNS
License: MIT
Author: Niels Wouda
Author-email: nielswouda@gmail.com
Requires-Python: >=3.8,<4.0
Classifier: Development Status :: 5 - Production/Stable
Classifier: Intended Audience :: Developers
Classifier: Intended Audience :: Science/Research
Classifier: License :: OSI Approved :: MIT License
Classifier: Programming Language :: Python :: 3
Classifier: Programming Language :: Python :: 3.8
Classifier: Programming Language :: Python :: 3.9
Classifier: Programming Language :: Python :: 3.10
Classifier: Programming Language :: Python :: 3.11
Classifier: Topic :: Scientific/Engineering
Classifier: Topic :: Software Development
Provides-Extra: mabwiser
Requires-Dist: mabwiser (>=2.7.1) ; extra == "mabwiser"
Requires-Dist: matplotlib (>=3.5.0)
Requires-Dist: numpy (>=1.18.0)
Project-URL: Repository, https://github.com/N-Wouda/ALNS
Project-URL: Tracker, https://github.com/N-Wouda/ALNS/issues
